{
  "webflow": {
    "siteId": "69d6045f113e53f87d5d2de9",
    "variables": [],
    "collections": [
      {
        "id": "collection-c66b35aa-9570-c662-dc9e-0cb425f14209",
        "name": "Base collection"
      }
    ],
    "styles": []
  },
  "figma": {
    "fileKey": "xHsj8iMfiQhpoIoAkSIRRp",
    "nodeId": "0:1",
    "colors": {
      "Grey": "#F4F6FC",
      "White": "#FFFFFF",
      "Dark blue": "#282938",
      "Yellow": "#FCD980",
      "Royal Blue": "#2405F2"
    },
    "typography": {
      "Paragraph": {
        "family": "Poppins",
        "style": "Regular",
        "size": "16px",
        "weight": 400,
        "lineHeight": "28px"
      },
      "Heading 2": {
        "family": "Poppins",
        "style": "SemiBold",
        "size": "48px",
        "weight": 600,
        "lineHeight": "64px"
      },
      "Heading 3": {
        "family": "Poppins",
        "style": "SemiBold",
        "size": "38px",
        "weight": 600,
        "lineHeight": "56px"
      },
      "Heading 6": {
        "family": "Poppins",
        "style": "Medium",
        "size": "24px",
        "weight": 500,
        "lineHeight": "36px"
      }
    }
  },
  "audit": {
    "status": "completed",
    "conflicts": [
      {
        "type": "Naming",
        "description": "Figma color names 'Dark blue', 'Royal Blue' contain spaces. Must be converted to kebab-case (e.g., color--dark-blue).",
        "severity": "High"
      },
      {
        "type": "Units",
        "description": "Figma typography uses 'px'. Must be converted to 'rem' for Client-First compliance.",
        "severity": "Medium"
      }
    ],
    "recommendations": {
      "color_variables": [
        { "name": "color--dark-blue", "hex": "#282938", "usage": "Main background / Heading text" },
        { "name": "color--royal-blue", "hex": "#2405F2", "usage": "Brand primary" },
        { "name": "color--yellow", "hex": "#FCD980", "usage": "Accent secondary" },
        { "name": "color--grey", "hex": "#F4F6FC", "usage": "Section background alternate" },
        { "name": "color--white", "hex": "#FFFFFF", "usage": "Base background" }
      ],
      "typography_styles": [
        { "tag": "All HTML Tags (Body)", "size": "1rem", "line_height": "1.75rem", "font": "Poppins" },
        { "tag": "All H2 Headers", "size": "3rem", "line_height": "4rem", "weight": "600" },
        { "tag": "All H3 Headers", "size": "2.375rem", "line_height": "3.5rem", "weight": "600" },
        { "tag": "All H6 Headers", "size": "1.5rem", "line_height": "2.25rem", "weight": "500" }
      ],
      "logic_notes": [
        "Use 'Tag-First' strategy for typography styles before applying utility classes.",
        "Ensure all spacing (gap, padding) found in components uses the 'rem' conversion (px/16).",
        "Create 'padding-global' and 'container-large' utility classes as part of the core structure setup."
      ]
    }
  }
}
